CompleteTheSquare/__init__.py
CompleteTheSquare/setup.py
CompleteTheSquare-1.2.dist-info/METADATA
CompleteTheSquare-1.2.dist-info/WHEEL
CompleteTheSquare-1.2.dist-info/top_level.txt
CompleteTheSquare-1.2.dist-info/RECORD
