Metadata-Version: 2.1
Name: CompleteTheSquare
Version: 1.2
Summary: A Simple Python project to complete the square!
Home-page: https://github.com/Zeliktric/CompleteTheSquare
Author: Zeliktric
Author-email: zeliktric@zeliktric.com
License: UNKNOWN
Platform: UNKNOWN
Classifier: Programming Language :: Python :: 3
Classifier: License :: OSI Approved :: MIT License
Classifier: Operating System :: OS Independent
Requires-Python: >=3.6
